gerador/__init__.py
gerador/nome.py
gerador-0.0.1.dist-info/LICENSE.txt
gerador-0.0.1.dist-info/METADATA
gerador-0.0.1.dist-info/WHEEL
gerador-0.0.1.dist-info/top_level.txt
gerador-0.0.1.dist-info/RECORD
