Metadata-Version: 2.1
Name: gerador
Version: 0.0.1
Summary: Pacote python para criar nomes para jogos de RPG.
Home-page: https://github.com/LeKeu/Gerador---Nomes-de-RPG
Author: Leticia Keuffer Cavalleiro de Macedo
Author-email: lekeuffer@gmail.com
License: MIT License
Keywords: Pacote
Platform: UNKNOWN
License-File: LICENSE.txt
